googleassistant_respeakerd/__init__.py
googleassistant_respeakerd/assist_with_respeakerd.py
googleassistant_respeakerd-0.1.2.dist-info/DESCRIPTION.rst
googleassistant_respeakerd-0.1.2.dist-info/METADATA
googleassistant_respeakerd-0.1.2.dist-info/RECORD
googleassistant_respeakerd-0.1.2.dist-info/WHEEL
googleassistant_respeakerd-0.1.2.dist-info/entry_points.txt
googleassistant_respeakerd-0.1.2.dist-info/metadata.json
googleassistant_respeakerd-0.1.2.dist-info/top_level.txt
