Metadata-Version: 2.0
Name: googleassistant-respeakerd
Version: 0.1.2
Summary: 
Requires-Dist: google-assistant-sdk[samples]
Requires-Dist: google-auth-oauthlib[tool]
Requires-Dist: pydbus (<1,>=0.6.0)
